s3adm/__init__.py
s3adm/_helpers.py
s3adm/api.py
s3adm/arguments.py
s3adm/cli.py
s3adm/py.typed
s3adm-0.1.0.dist-info/METADATA
s3adm-0.1.0.dist-info/WHEEL
s3adm-0.1.0.dist-info/entry_points.txt
s3adm-0.1.0.dist-info/RECORD
