Metadata-Version: 2.4
Name: s3adm
Version: 0.1.0
Summary: Ceph S3 admin api
Requires-Python: >=3.9
Requires-Dist: httpx-auth>=0.23.1
Requires-Dist: httpx>=0.28.1
Requires-Dist: tabulate>=0.9.0
